PyDiffGame/ContinuousPyDiffGame.py
PyDiffGame/DiscretePyDiffGame.py
PyDiffGame/LQR.py
PyDiffGame/Objective.py
PyDiffGame/PyDiffGame.py
PyDiffGame/PyDiffGameLQRComparison.py
PyDiffGame/__init__.py
PyDiffGame/examples/InvertedPendulumComparison.py
PyDiffGame/examples/MassesWithSpringsComparison.py
PyDiffGame/examples/PVTOL.py
PyDiffGame/examples/PVTOLComparison.py
PyDiffGame/examples/QuadRotorControl.py
PyDiffGame/examples/figures/PVTOL0001.png
PyDiffGame/examples/figures/PVTOL001.png
PyDiffGame/examples/figures/PVTOL01.png
PyDiffGame/examples/figures/PVTOL1.png
PyDiffGame/examples/figures/2/2-players_large_1.png
PyDiffGame/examples/figures/2/2-players_large_2.png
PyDiffGame/examples/figures/2/LQR_large_1.png
PyDiffGame/examples/figures/2/LQR_large_2.png
PyDiffGame/examples/figures/2/two_masses_tikz.png
PyDiffGame/examples/figures/4/4-players_large_1.png
PyDiffGame/examples/figures/4/4-players_large_2.png
PyDiffGame/examples/figures/4/LQR_large_1.png
PyDiffGame/examples/figures/4/LQR_large_2.png
PyDiffGame/examples/figures/8/8-players_large_1.png
PyDiffGame/examples/figures/8/8-players_large_2.png
PyDiffGame/examples/figures/8/LQR_large_1.png
PyDiffGame/examples/figures/8/LQR_large_2.png
PyDiffGame/examples/figures/PVTOL/PVTOL1.png
PyDiffGame/examples/figures/PVTOL/PVTOL10.png
PyDiffGame/examples/figures/PVTOL/PVTOL100.png
PyDiffGame/examples/figures/PVTOL/PVTOL1000.png
pydiffgame-1.0.0.dist-info/METADATA
pydiffgame-1.0.0.dist-info/WHEEL
pydiffgame-1.0.0.dist-info/licenses/LICENSE
pydiffgame-1.0.0.dist-info/RECORD
