Metadata-Version: 2.4
Name: PyDiffGame
Version: 1.0.0
Summary: PyDiffGame is a Python implementation of a Nash Equilibrium solution to Differential Games, based on a reduction of Game Hamilton-Bellman-Jacobi (GHJB) equations to Game Algebraic and Differential Riccati equations, associated with Multi-Objective Dynamical Control Systems
Project-URL: Homepage, https://krichelj.github.io/PyDiffGame/
Project-URL: Bug Tracker, https://github.com/krichelj/PyDiffGame/issues
Author-email: Joshua Shay Kricheli <skricheli2@gmail.com>
License-File: LICENSE
Classifier: License :: OSI Approved :: MIT License
Classifier: Operating System :: OS Independent
Classifier: Programming Language :: Python :: 3
Requires-Python: >=3.10
